Workbook

Sheet Final_Analysis_Dataset
A1: Year | B1: 2BD_HP% | C1: 3BD_HP% | D1: MPR% | E1: Money Supply M2(Trillion) | F1: Cash_Reserve_Ratio% | G1: Liquidity_Ratio%
A2: 2010 | B2: =Housing_Performance!F2 -> 0.019368218 | C2: =Housing_Performance!K2 -> 0.012199634 | D2: 6.25 | E2: 11.034 | F2: 2 | G2: 30
A3: 2011 | B3: =Housing_Performance!F3 -> 0.16267163 | C3: =Housing_Performance!K3 -> 0.14279414 | D3: 12 | E3: 12.641 | F3: 8 | G3: 30
A4: 2012 | B4: =Housing_Performance!F4 -> 0.14748516 | C4: =Housing_Performance!K4 -> 0.13487961 | D4: 12 | E4: 15.336 | F4: 12 | G4: 30
A5: 2013 | B5: =Housing_Performance!F5 -> 0.14105691 | C5: =Housing_Performance!K5 -> 0.13137859 | D5: 12 | E5: 16.44 | F5: 12 | G5: 30
A6: 2014 | B6: =Housing_Performance!F6 -> 0.13174372 | C6: =Housing_Performance!K6 -> 0.13280997 | D6: 13 | E6: 17.68 | F6: 15 | G6: 30
A7: 2015 | B7: =Housing_Performance!F7 -> 0.11715233 | C7: =Housing_Performance!K7 -> 0.15816765 | D7: 11 | E7: 18.724 | F7: 20 | G7: 30
A8: 2016 | B8: =Housing_Performance!F8 -> 0.1307295 | C8: =Housing_Performance!K8 -> 0.14272364 | D8: 14 | E8: 23.141 | F8: 22.5 | G8: 30
A9: 2017 | B9: =Housing_Performance!F9 -> 0.13465601 | C9: =Housing_Performance!K9 -> 0.14875881 | D9: 14 | E9: 21.854 | F9: 22.5 | G9: 30
A10: 2018 | B10: =Housing_Performance!F10 -> 0.18641256 | C10: =Housing_Performance!K10 -> 0.1299215 | D10: 14 | E10: 26.584 | F10: 22.5 | G10: 30
A11: 2019 | B11: =Housing_Performance!F11 -> 0.17332184 | C11: =Housing_Performance!K11 -> 0.10894448 | D11: 13.5 | E11: 27.028 | F11: 22.5 | G11: 30
A12: 2020 | B12: =Housing_Performance!F12 -> 0.16935616 | C12: =Housing_Performance!K12 -> 0.12947654 | D12: 11.5 | E12: 32.468 | F12: 27.5 | G12: 30
A13: 2021 | B13: =Housing_Performance!F13 -> 0.21889777 | C13: =Housing_Performance!K13 -> 0.10310958 | D13: 11.5 | E13: 41.702 | F13: 27.5 | G13: 30
... A17: 2025 | B17: =Housing_Performance!F17 -> 0.26314837 | C17: =Housing_Performance!K17 -> 0.17686599 | D17: 27 | E17: 115 | F17: 48 | G17: 30

Sheet Housing_Performance
A1: Year | B1: 2BD_Rental | C1: 2BD_Capital | D1: 2BD_IR% | E1: 2BD_CR% | F1: 2BD_HP% | G1: 3BD_Rental | H1: 3BD_Capital | I1: 3BD_IR% | J1: 3BD_CR% | K1: 3BD_HP%
A2: 2010 | B2: 99857 | C2: 5155714.3 | D2: =B2/C2 -> 0.019368218 | E2: 0 | F2: =D2+E2 -> 0.019368218 | G2: 176154 | H2: 14439286 | I2: =G2/H2 -> 0.012199634 | J2: 0 | K2: =I2+J2 -> 0.012199634
A3: 2011 | B3: 132071.43 | C3: 5878571.4 | D3: =B3/C3 -> 0.022466586 | E3: =(C3-C2)/C2 -> 0.14020504 | F3: =D3+E3 -> 0.16267163 | G3: 187143 | H3: 16335714 | I3: =G3/H3 -> 0.011456065 | J3: =(H3-H2)/H2 -> 0.13133807 | K3: =I3+J3 -> 0.14279414
A4: 2012 | B4: 146142.86 | C4: 6615714.3 | D4: =B4/C4 -> 0.022090261 | E4: =(C4-C3)/C3 -> 0.1253949 | F4: =D4+E4 -> 0.14748516 | G4: 224286 | H4: 18339286 | I4: =G4/H4 -> 0.012229811 | J4: =(H4-H3)/H3 -> 0.1226498 | K4: =I4+J4 -> 0.13487961
A5: 2013 | B5: 162642.86 | C5: 7403571.4 | D5: =B5/C5 -> 0.021968162 | E5: =(C5-C4)/C4 -> 0.11908875 | F5: =D5+E5 -> 0.14105691 | G5: 254286 | H5: 20521429 | I5: =G5/H5 -> 0.012391242 | J5: =(H5-H4)/H4 -> 0.11898735 | K5: =I5+J5 -> 0.13137859
A6: 2014 | B6: 192000 | C6: 8205714.3 | D6: =B6/C6 -> 0.023398329 | E6: =(C6-C5)/C5 -> 0.10834539 | F6: =D6+E6 -> 0.13174372 | G6: 288571 | H6: 22989286 | I6: =G6/H6 -> 0.012552412 | J6: =(H6-H5)/H5 -> 0.12025756 | K6: =I6+J6 -> 0.13280997
A7: 2015 | B7: 213857 | C7: 8971428.6 | D7: =B7/C7 -> 0.023837564 | E7: =(C7-C6)/C6 -> 0.093314763 | F7: =D7+E7 -> 0.11715233 | G7: 315714 | H7: 26350000 | I7: =G7/H7 -> 0.011981556 | J7: =(H7-H6)/H6 -> 0.1461861 | K7: =I7+J7 -> 0.15816765
A8: 2016 | B8: 250285.71 | C8: 9917857.1 | D8: =B8/C8 -> 0.025235866 | E8: =(C8-C7)/C7 -> 0.10549363 | F8: =D8+E8 -> 0.1307295 | G8: 371429 | H8: 29782143 | I8: =G8/H8 -> 0.012471534 | J8: =(H8-H7)/H7 -> 0.13025211 | K8: =I8+J8 -> 0.14272364
A9: 2017 | B9: 281000 | C9: 11000000 | D9: =B9/C9 -> 0.025545455 | E9: =(C9-C8)/C8 -> 0.10911055 | F9: =D9+E9 -> 0.13465601 | G9: 445714 | H9: 33820000 | I9: =G9/H9 -> 0.013179007 | J9: =(H9-H8)/H8 -> 0.1355798 | K9: =I9+J9 -> 0.14875881
A10: 2018 | B10: 320000 | C10: 12775000 | D10: =B10/C10 -> 0.025048924 | E10: =(C10-C9)/C9 -> 0.16136364 | F10: =D10+E10 -> 0.18641256 | G10: 517857 | H10: 37750000 | I10: =G10/H10 -> 0.013718066 | J10: =(H10-H9)/H9 -> 0.11620343 | K10: =I10+J10 -> 0.1299215
A11: 2019 | B11: 364928.57 | C11: 14671429 | D11: =B11/C11 -> 0.024873418 | E11: =(C11-C10)/C10 -> 0.14844842 | F11: =D11+E11 -> 0.17332184 | G11: 588571 | H11: 41325000 | I11: =G11/H11 -> 0.014242492 | J11: =(H11-H10)/H10 -> 0.094701987 | K11: =I11+J11 -> 0.10894448
A12: 2020 | B12: 427785.71 | C12: 16782143 | D12: =B12/C12 -> 0.02549053 | E12: =(C12-C11)/C11 -> 0.14386563 | F12: =D12+E12 -> 0.16935616 | G12: 705000 | H12: 46042857 | I12: =G12/H12 -> 0.015311821 | J12: =(H12-H11)/H11 -> 0.11416472 | K12: =I12+J12 -> 0.12947654
A13: 2021 | B13: 501428.57 | C13: 20035714 | D13: =B13/C13 -> 0.025026738 | E13: =(C13-C12)/C12 -> 0.19387104 | F13: =D13+E13 -> 0.21889777 | G13: 808571 | H13: 50046429 | I13: =G13/H13 -> 0.016156417 | J13: =(H13-H12)/H12 -> 0.086953162 | K13: =I13+J13 -> 0.10310958
A14: 2022 | B14: 657142.86 | C14: 24467857 | D14: =B14/C14 -> 0.026857393 | E14: =(C14-C13)/C13 -> 0.22121212 | F14: =D14+E14 -> 0.24806951 | G14: 1032143 | H14: 57335714 | I14: =G14/H14 -> 0.018001747 | J14: =(H14-H13)/H13 -> 0.14565045 | K14: =I14+J14 -> 0.1636522
... A17: 2025 | B17: 1150000 | C17: 44692857 | D17: =B17/C17 -> 0.025731181 | E17: =(C17-C16)/C16 -> 0.23741719 | F17: =D17+E17 -> 0.26314837 | G17: 2092857 | H17: 92485714 | I17: =G17/H17 -> 0.022628976 | J17: =(H17-H16)/H16 -> 0.15423701 | K17: =I17+J17 -> 0.17686599

Sheet Monetary_Policy_Data
A1: Year | B1: MPR% | C1: Money_Supply_M2 | D1: Cash_Reserve_Ratio% | E1: Liquidity_Ratio%
A2: 2010 | B2: 6.25 | C2: 11.034 | D2: 2 | E2: 30
A3: 2011 | B3: 12 | C3: 12.641 | D3: 8 | E3: 30
A4: 2012 | B4: 12 | C4: 15.336 | D4: 12 | E4: 30
A5: 2013 | B5: 12 | C5: 16.44 | D5: 12 | E5: 30
A6: 2014 | B6: 13 | C6: 17.68 | D6: 15 | E6: 30
A7: 2015 | B7: 11 | C7: 18.724 | D7: 20 | E7: 30
A8: 2016 | B8: 14 | C8: 23.141 | D8: 22.5 | E8: 30
A9: 2017 | B9: 14 | C9: 21.854 | D9: 22.5 | E9: 30
A10: 2018 | B10: 14 | C10: 26.584 | D10: 22.5 | E10: 30
A11: 2019 | B11: 13.5 | C11: 27.028 | D11: 22.5 | E11: 30
A12: 2020 | B12: 11.5 | C12: 32.468 | D12: 27.5 | E12: 30
A13: 2021 | B13: 11.5 | C13: 41.702 | D13: 27.5 | E13: 30
... A17: 2025 | B17: 27 | C17: 115 | D17: 48 | E17: 30

Sheet Correlation_Analysis
B1: 2BD_HP% | C1: 3BD_HP% | D1: MPR% | E1: Money_Supply_M2 | F1: Cash_Reserve_Ratio% | G1: Liquidity_Ratio% | H1: Inflation% | I1: Exchange_Rate | J1: GDP_Growth%
A2: 2BD_HP% | B2: 1 | C2: 0.64346804 | D2: 0.56085904 | E2: 0.79484064 | F2: 0.87051675 | H2: 0.69911823 | I2: 0.69637668 | J2: -0.54722368
A3: 3BD_HP% | B3: 0.64346804 | C3: 1 | D3: 0.69352805 | E3: 0.59340519 | F3: 0.54592649 | H3: 0.54943405 | I3: 0.57656124 | J3: -0.37844188
A4: MPR% | B4: 0.56085904 | C4: 0.69352805 | D4: 1 | E4: 0.69474386 | F4: 0.73646634 | H4: 0.59487161 | I4: 0.71184772 | J4: -0.58520183
A5: Money_Supply_M2 | B5: 0.79484064 | C5: 0.59340519 | D5: 0.69474386 | E5: 1 | F5: 0.82803426 | H5: 0.90095256 | I5: 0.97379611 | J5: -0.37162925
A6: Cash_Reserve_Ratio% | B6: 0.87051675 | C6: 0.54592649 | D6: 0.73646634 | E6: 0.82803426 | F6: 1 | H6: 0.6851122 | I6: 0.74394846 | J6: -0.71799449
A7: Liquidity_Ratio%
A8: Inflation% | B8: 0.69911823 | C8: 0.54943405 | D8: 0.59487161 | E8: 0.90095256 | F8: 0.6851122 | H8: 1 | I8: 0.91743228 | J8: -0.39274039
A9: Exchange_Rate | B9: 0.69637668 | C9: 0.57656124 | D9: 0.71184772 | E9: 0.97379611 | F9: 0.74394846 | H9: 0.91743228 | I9: 1 | J9: -0.35011658
A10: GDP_Growth% | B10: -0.54722368 | C10: -0.37844188 | D10: -0.58520183 | E10: -0.37162925 | F10: -0.71799449 | H10: -0.39274039 | I10: -0.35011658 | J10: 1

Sheet Respondent_Data
A1: ID | B1: Experience | C1: Market_Familiarity | D1: Gender | E1: Age_Group | F1: Position | G1: Firm_Age | H1: Policy_Observation
A2: 1 | B2: Above 20 years | C2: Somewhat familiar | D2: Female | E2: Above 60 | F2: Senior Partner | G2: 21 | H2: M2 growth correlates with property price increases
A3: 2 | B3: 16-20 years | C3: Somewhat familiar | D3: Male | E3: Below 30 | F3: Principal Partner | G3: 11 | H3: Tight monetary policy reduces housing demand
A4: 3 | B4: 11 -15 years | C4: Very familiar | D4: Female | E4: 51-60 | F4: Senior Surveyor | G4: 8 | H4: High CRR limits bank lending to real estate
A5: 4 | B5: Less than 5 years | C5: Somewhat familiar | D5: Male | E5: 41-50 | F5: Surveyor | G5: 25 | H5: High inflation pushes rental yields up
A6: 5 | B6: 16-20 years | C6: Very familiar | D6: Female | E6: Below 30 | F6: Managing Partner | G6: 30 | H6: High inflation pushes rental yields up
A7: 6 | B7: Less than 5 years | C7: Somewhat familiar | D7: Female | E7: 31-40 | F7: Estate Manager | G7: 29 | H7: High inflation pushes rental yields up
A8: 7 | B8: 11 -15 years | C8: Very familiar | D8: Male | E8: Above 60 | F8: Partner | G8: 19 | H8: High CRR limits bank lending to real estate
A9: 8 | B9: 11 -15 years | C9: Very familiar | D9: Male | E9: 31-40 | F9: Head of Department | G9: 8 | H9: High CRR limits bank lending to real estate
A10: 9 | B10: 16-20 years | C10: Somewhat familiar | D10: Female | E10: 51-60 | F10: Managing Partner | G10: 16 | H10: Tight monetary policy reduces housing demand
A11: 10 | B11: 16-20 years | C11: Very familiar | D11: Female | E11: 31-40 | F11: Principal Partner | G11: 7 | H11: Exchange rate volatility affects construction costs
A12: 11 | B12: 11 -15 years | C12: Somewhat familiar | D12: Male | E12: Below 30 | F12: Partner | G12: 16 | H12: Tight monetary policy reduces housing demand
A13: 12 | B13: 11 -15 years | C13: Very familiar | D13: Female | E13: Above 60 | F13: Senior Surveyor | G13: 8 | H13: Tight monetary policy reduces housing demand
... A96: 95 | B96: 16-20 years | C96: Somewhat familiar | D96: Female | E96: Below 30 | F96: Principal Partner | G96: 11 | H96: MPR increases reduce mortgage accessibility

Sheet Research_Objectives
A1: Objective | B1: Hypothesis | C1: Expected_Relationship | D1: Data_Used | E1: Analysis_Method
A2: Effect of MPR on housing performance | B2: Increase in MPR negatively affects housing performance | C2: Negative correlation | D2: MPR% and Housing Performance% (2010-2025) | E2: Regression Analysis
A3: Effect of Money Supply (M2) on housing performance | B3: Increase in M2 positively affects housing performance | C3: Positive correlation | D3: M2 Growth and Housing Performance% | E3: Correlation Analysis
A4: Effect of Liquidity Ratio on housing performance | B4: Higher liquidity ratio may constrain housing finance | C4: Negative correlation | D4: Liquidity Ratio% and Housing Performance% | E4: Time Series Analysis
A5: Effect of Cash Reserve Ratio on housing performance | B5: Higher CRR reduces bank lending to housing sector | C5: Negative correlation | D5: CRR% and Housing Performance% | E5: Comparative Analysis

Sheet Formulas_Definitions
A1: Term | B1: Formula | C1: Measurement | D1: Expected_Impact_on_Housing
A2: HP (Housing Performance) | B2: IR% + CR% | C2: Percentage (%) | D2: Dependent variable
A3: IR (Income Return) | B3: (Annual Rental Income / Capital Value) × 100 | C3: Percentage (%) | D3: Affected by rental market conditions
A4: CR (Capital Return) | B4: ((Current CV - Previous CV) / Previous CV) × 100 | C4: Percentage (%) | D4: Affected by property price appreciation
A5: MPR | B5: Central Bank policy interest rate | C5: Percentage (%) | D5: Affects mortgage interest rates
A6: M2 | B6: Broad money supply measure | C6: Trillion Naira (₦T) | D6: Affects credit availability
A7: CRR | B7: Percentage of deposits banks must hold with central bank | C7: Percentage (%) | D7: Affects bank lending capacity
A8: Liquidity Ratio | B8: Minimum liquid assets banks must maintain | C8: Percentage (%) | D8: Affects bank liquidity for housing loans
